called/__init__.py
called/openai_function.py
called-0.0.8.dist-info/METADATA
called-0.0.8.dist-info/WHEEL
called-0.0.8.dist-info/licenses/LICENSE
called-0.0.8.dist-info/RECORD
